rda_python_setuid/__init__.py
rda_python_setuid/pgstart.py
rda_python_setuid/pywrapper.c
rda_python_setuid/pywrapper.py
rda_python_setuid-1.0.3.dist-info/licenses/LICENSE
rda_python_setuid-1.0.3.dist-info/METADATA
rda_python_setuid-1.0.3.dist-info/WHEEL
rda_python_setuid-1.0.3.dist-info/entry_points.txt
rda_python_setuid-1.0.3.dist-info/top_level.txt
rda_python_setuid-1.0.3.dist-info/RECORD
